cmip6_preprocessing/__init__.py
cmip6_preprocessing/_version.py
cmip6_preprocessing/drift_removal.py
cmip6_preprocessing/grids.py
cmip6_preprocessing/junit.xml
cmip6_preprocessing/postprocessing.py
cmip6_preprocessing/preprocessing.py
cmip6_preprocessing/regionmask.py
cmip6_preprocessing/utils.py
cmip6_preprocessing/specs/staggered_grid_config.yaml
tests/__init__.py
tests/conftest.py
tests/test_drift_removal.py
tests/test_grids.py
tests/test_postprocessing.py
tests/test_preprocessing.py
tests/test_preprocessing_cloud.py
tests/test_regionmask.py
tests/test_utils.py
cmip6_preprocessing-0.6.0.dist-info/LICENSE.txt
cmip6_preprocessing-0.6.0.dist-info/METADATA
cmip6_preprocessing-0.6.0.dist-info/WHEEL
cmip6_preprocessing-0.6.0.dist-info/top_level.txt
cmip6_preprocessing-0.6.0.dist-info/RECORD
