Metadata-Version: 2.1
Name: cmip6-preprocessing
Version: 0.6.0
Summary: Analysis ready CMIP6 data the easy way
Home-page: https://github.com/jbusecke/cmip6_preprocessing
Author: cmip6_preprocessing developers
Author-email: jbusecke@princeton.edu
License: MIT
Platform: UNKNOWN
Classifier: Development Status :: 4 - Beta
Classifier: Topic :: Scientific/Engineering
Classifier: Intended Audience :: Science/Research
Classifier: Operating System :: OS Independent
Classifier: Programming Language :: Python
Classifier: Programming Language :: Python :: 3
Classifier: Programming Language :: Python :: 3.7
Classifier: Programming Language :: Python :: 3.8
Classifier: Programming Language :: Python :: 3.9
Classifier: License :: OSI Approved :: MIT License
Requires-Python: >=3.7
Requires-Dist: numpy
Requires-Dist: pandas
Requires-Dist: xarray (>=0.17.0)
Requires-Dist: xgcm (<0.7.0)
Requires-Dist: cftime
Requires-Dist: xarrayutils
Requires-Dist: pint
Requires-Dist: cf-xarray (>=0.6.0)
Requires-Dist: pint-xarray
